Workbook

Sheet Estimated Budget
A1: Strategy | B1: Description | C1: Total Patients | D1: Enrolled | E1: Unenrolled | F1: Estimated Budget
A2: 1:2 | B2: 1:2 randomization – 400 patients | C2: 400 | D2: 200 | E2: 200 | F2: =D22 -> 70800000
A3: 1:3 | B3: 1:3 randomization – 600 patients | C3: 600 | D3: 200 | E3: 400 | F3: =E22 -> 73800000
A4: 1:5 | B4: 1:5 randomization – 1,000 patients | C4: 1000 | D4: 200 | E4: 800 | F4: =F22 -> 79800000
A5: 1:1 (200) | B5: No randomization – 200 patients | C5: 200 | D5: 200 | E5: 0 | F5: =G22 -> 67800000
A6: 1:1 (1,000) | B6: No randomization – 1,000 patients | C6: 1000 | D6: 1000 | E6: 0 | F6: =H22 -> 187800000
A10: Line Item | B10: Estimated Price | C10: Three Visits | D10: 1:2 | E10: 1:3 | F10: 1:5 | G10: 1:1 (200) | H10: 1:1 (1,000)
A11: Laboratory Test | B11: 20000 | C11: =B11*3 -> 60000 | D11: =$C11*INDEX($D$2:$D$6,COLUMNS($D:D)) -> 12000000 | E11: =$C11*INDEX($D$2:$D$6,COLUMNS($D:E)) -> 12000000 | F11: =$C11*INDEX($D$2:$D$6,COLUMNS($D:F)) -> 12000000 | G11: =$C11*INDEX($D$2:$D$6,COLUMNS($D:G)) -> 12000000 | H11: =$C11*INDEX($D$2:$D$6,COLUMNS($D:H)) -> 60000000
A12: Radiologist Payment | B12: 20000 | D12: =$B12*INDEX($D$2:$D$6,COLUMNS($D:D)) -> 4000000 | E12: =$B12*INDEX($D$2:$D$6,COLUMNS($D:E)) -> 4000000 | F12: =$B12*INDEX($D$2:$D$6,COLUMNS($D:F)) -> 4000000 | G12: =$B12*INDEX($D$2:$D$6,COLUMNS($D:G)) -> 4000000 | H12: =$B12*INDEX($D$2:$D$6,COLUMNS($D:H)) -> 20000000
A13: Payment for Enrolled Patients | B13: 20000 | C13: =B13*3 -> 60000 | D13: =$C13*INDEX($D$2:$D$6,COLUMNS($D:D)) -> 12000000 | E13: =$C13*INDEX($D$2:$D$6,COLUMNS($D:E)) -> 12000000 | F13: =$C13*INDEX($D$2:$D$6,COLUMNS($D:F)) -> 12000000 | G13: =$C13*INDEX($D$2:$D$6,COLUMNS($D:G)) -> 12000000 | H13: =$C13*INDEX($D$2:$D$6,COLUMNS($D:H)) -> 60000000
A14: Payment for Unenrolled Patients | B14: 15000 | D14: =$B14*INDEX($E$2:$E$6,COLUMNS($D:D)) -> 3000000 | E14: =$B14*INDEX($E$2:$E$6,COLUMNS($D:E)) -> 6000000 | F14: =$B14*INDEX($E$2:$E$6,COLUMNS($D:F)) -> 12000000 | G14: =$B14*INDEX($E$2:$E$6,COLUMNS($D:G)) -> 0 | H14: =$B14*INDEX($E$2:$E$6,COLUMNS($D:H)) -> 0
A15: Transport for Enrolled Patients | B15: 10000 | D15: =$B15*INDEX($D$2:$D$6,COLUMNS($D:D)) -> 2000000 | E15: =$B15*INDEX($D$2:$D$6,COLUMNS($D:E)) -> 2000000 | F15: =$B15*INDEX($D$2:$D$6,COLUMNS($D:F)) -> 2000000 | G15: =$B15*INDEX($D$2:$D$6,COLUMNS($D:G)) -> 2000000 | H15: =$B15*INDEX($D$2:$D$6,COLUMNS($D:H)) -> 10000000
A16: Enrollment Milestone (Partial) | B16: 3000000 | C16: 4 | D16: =$B16*$C16 -> 12000000 | E16: =$B16*$C16 -> 12000000 | F16: =$B16*$C16 -> 12000000 | G16: =$B16*$C16 -> 12000000 | H16: =$B16*$C16 -> 12000000
A17: Enrollment Milestone (Full) | B17: 1500000 | C17: 4 | D17: =$B17*$C17 -> 6000000 | E17: =$B17*$C17 -> 6000000 | F17: =$B17*$C17 -> 6000000 | G17: =$B17*$C17 -> 6000000 | H17: =$B17*$C17 -> 6000000
A18: Study Close | B18: 1500000 | C18: 4 | D18: =$B18*$C18 -> 6000000 | E18: =$B18*$C18 -> 6000000 | F18: =$B18*$C18 -> 6000000 | G18: =$B18*$C18 -> 6000000 | H18: =$B18*$C18 -> 6000000
A19: Ultrasound Scan Machine | B19: 1500000 | C19: 4 | D19: =$B19*$C19 -> 6000000 | E19: =$B19*$C19 -> 6000000 | F19: =$B19*$C19 -> 6000000 | G19: =$B19*$C19 -> 6000000 | H19: =$B19*$C19 -> 6000000
A20: Site Administrators | B20: 1200000 | C20: 4 | D20: =$B20*$C20 -> 4800000 | E20: =$B20*$C20 -> 4800000 | F20: =$B20*$C20 -> 4800000 | G20: =$B20*$C20 -> 4800000 | H20: =$B20*$C20 -> 4800000
A21: Miscellaneous | B21: 3000000 | C21: 1 | D21: =$B21*$C21 -> 3000000 | E21: =$B21*$C21 -> 3000000 | F21: =$B21*$C21 -> 3000000 | G21: =$B21*$C21 -> 3000000 | H21: =$B21*$C21 -> 3000000
A22: Total | B22: =SUM(B11:B21) -> 11785000 | D22: =SUM(D11:D21) -> 70800000 | E22: =SUM(E11:E21) -> 73800000 | F22: =SUM(F11:F21) -> 79800000 | G22: =SUM(G11:G21) -> 67800000 | H22: =SUM(H11:H21) -> 187800000

Sheet Summary Data
A1: Price Scenario | B1: Sampling Strategy | C1: Eligible Patients | D1: Attrition | E1: Drug Price | F1: Drug Purchase | G1: Purchase Period (Months) | H1: Total Purchases | I1: Cost of Research | J1: Net Result | K1: Result
A2: High | B2: 1:2 | C2: =VLOOKUP(B2,$A$11:$F$16,5,FALSE) -> 200 | D2: =C2*0.7 -> 140 | E2: =VLOOKUP(A2,$C$12:$D$15,2,FALSE) -> 32000 | F2: =E2*D2 -> 4480000 | G2: =VLOOKUP(A2,C$11:F$16,4,FALSE) -> 12 | H2: =F2*G2 -> 53760000 | I2: =VLOOKUP(A12,'Estimated Budget'!$A$2:$F$6,6,FALSE) -> 70800000 | J2: =I2-H2 -> 17040000 | K2: =IF(J2<0,"Profit",IF(J2>0,"Loss","Breakeven")) -> Loss
A3: High | B3: 1:3 | C3: =VLOOKUP(B3,$A$11:$F$16,5,FALSE) -> 400 | D3: =C3*0.7 -> 280 | E3: =VLOOKUP(A3,$C$12:$D$15,2,FALSE) -> 32000 | F3: =E3*D3 -> 8960000 | G3: =VLOOKUP(A3,C$11:F$16,4,FALSE) -> 12 | H3: =F3*G3 -> 107520000 | I3: =VLOOKUP(A13,'Estimated Budget'!$A$2:$F$6,6,FALSE) -> 73800000 | J3: =I3-H3 -> -33720000 | K3: =IF(J3<0,"Profit",IF(J3>0,"Loss","Breakeven")) -> Profit
A4: High | B4: 1:5 | C4: =VLOOKUP(B4,$A$11:$F$16,5,FALSE) -> 600 | D4: =C4*0.7 -> 420 | E4: =VLOOKUP(A4,$C$12:$D$15,2,FALSE) -> 32000 | F4: =E4*D4 -> 13440000 | G4: =VLOOKUP(A4,C$11:F$16,4,FALSE) -> 12 | H4: =F4*G4 -> 161280000 | I4: =VLOOKUP(A14,'Estimated Budget'!$A$2:$F$6,6,FALSE) -> 79800000 | J4: =I4-H4 -> -81480000 | K4: =IF(J4<0,"Profit",IF(J4>0,"Loss","Breakeven")) -> Profit
A5: High | B5: 1:1 (200) | C5: =VLOOKUP(B5,$A$11:$F$16,5,FALSE) -> 200 | D5: =C5*0.7 -> 140 | E5: =VLOOKUP(A5,$C$12:$D$15,2,FALSE) -> 32000 | F5: =E5*D5 -> 4480000 | G5: =VLOOKUP(A5,C$11:F$16,4,FALSE) -> 12 | H5: =F5*G5 -> 53760000 | I5: =VLOOKUP(A15,'Estimated Budget'!$A$2:$F$6,6,FALSE) -> 67800000 | J5: =I5-H5 -> 14040000 | K5: =IF(J5<0,"Profit",IF(J5>0,"Loss","Breakeven")) -> Loss
A6: High | B6: 1:1 (1,000) | C6: =VLOOKUP(B6,$A$11:$F$16,5,FALSE) -> 1000 | D6: =C6*0.7 -> 700 | E6: =VLOOKUP(A6,$C$12:$D$15,2,FALSE) -> 32000 | F6: =E6*D6 -> 22400000 | G6: =VLOOKUP(A6,C$11:F$16,4,FALSE) -> 12 | H6: =F6*G6 -> 268800000 | I6: =VLOOKUP(A16,'Estimated Budget'!$A$2:$F$6,6,FALSE) -> 187800000 | J6: =I6-H6 -> -81000000 | K6: =IF(J6<0,"Profit",IF(J6>0,"Loss","Breakeven")) -> Profit
A10: LookUp Table
A11: Strategy | B11: Cost of Research | C11: Price Scenario | D11: Drug Price | E11: Sample Size | F11: Months
A12: 1:2 | B12: =I2 -> 70800000 | C12: High | D12: 32000 | E12: 200 | F12: 12
A13: 1:3 | B13: =I3 -> 73800000 | C13: Medium | D13: 25000 | E13: 400
A14: 1:5 | B14: =I4 -> 79800000 | C14: Low | D14: 20000 | E14: 600
A15: 1:1 (200) | B15: =I5 -> 67800000 | C15: — | D15: — | E15: 200
A16: 1:1 (1,000) | B16: =I6 -> 187800000 | C16: — | D16: — | E16: 1000
